cicu
