Metadata-Version: 1.0
Name: clean-image-crop-uploader
Version: 0.2.2
Summary: Clean Image Crop Uploader (CICU) provides AJAX file upload and image CROP functionalities for ImageFields with a simple widget replacement in the form. It use Modal from twitter-bootstrap.
Home-page: UNKNOWN
Author: asagli
Author-email: alfredo.saglimbeni@gmail.com
License: UNKNOWN
Platform: UNKNOWN
Classifier: Development Status :: 4 - Beta
Classifier: Environment :: Web Environment
Classifier: Framework :: Django
Classifier: Intended Audience :: Developers
Classifier: Operating System :: OS Independent
Classifier: Programming Language :: Python
Classifier: Topic :: Software Development :: Libraries :: Python Modules
